[
  {
    "name": "E Mess",
    "vegOnly": true,
    "mon": {
      "breakfast": [
        "Poori",
        "Aloo Sabji",
        "Tea",
        "Coffee",
        "Milk",
        "Bread",
        "Butter",
        "Jam"
      ],
      "lunch": [
        "Aloo Matar",
        "Rice",
        "Dal",
        "Sambar",
        "Veg Salad",
        "Pickle",
        "Chapathi"
      ],
      "snacks": ["Samosa", "Tea", "Coffee"],
      "dinner": ["Bhindi Fry", "Dal Fry", "Jeera Rice", "Pickle", "Chapathi"]
    },
    "tue": {
      "breakfast": [
        "Masala Dosa",
        "Chutney",
        "Sambar",
        "Tea",
        "Coffee",
        "Milk",
        "Bread",
        "Butter",
        "Jam"
      ],
      "lunch": [
        "Palak Paneer",
        "Rice",
        "Dal",
        "Sambar",
        "Veg Salad",
        "Pickle",
        "Chapathi"
      ],
      "snacks": ["Kachori", "Tea", "Coffee"],
      "dinner": [
        "Aloo Bhujiya",
        "Sweet",
        "Dal",
        "Rice",
        "Chapathi",
        "Buttermilk",
        "Pickle"
      ]
    },
    "wed": {
      "breakfast": [
        "Poori",
        "Aloo Sabji",
        "Tea",
        "Coffee",
        "Milk",
        "Bread",
        "Butter",
        "Jam"
      ],
      "lunch": [
        "Aloo Gobi",
        "Pappad",
        "Rice",
        "Dal",
        "Sambar",
        "Veg Salad",
        "Pickle",
        "Chapathi"
      ],
      "snacks": ["Bonda", "Tea", "Coffee"],
      "dinner": [
        "Khichadi",
        "Matar Paneer",
        "Rice",
        "Dal",
        "Chapathi",
        "Pickle"
      ]
    },
    "thu": {
      "breakfast": [
        "Utthappam",
        "Chutney",
        "Sambar",
        "Tea",
        "Coffee",
        "Milk",
        "Bread",
        "Butter",
        "Jam"
      ],
      "lunch": [
        "Mix Veg Sabji",
        "Kadi Pokkuvada",
        "Rice",
        "Dal",
        "Sambar",
        "Veg Salad",
        "Pickle",
        "Chapathi"
      ],
      "snacks": ["Samosa", "Tea", "Coffee"],
      "dinner": ["Gobi Manchurian", "Rice", "Dal", "Chapathi", "Pickle"]
    },
    "fri": {
      "breakfast": [
        "Poha",
        "Mixture",
        "Sauce",
        "Tea",
        "Coffee",
        "Milk",
        "Bread",
        "Butter",
        "Jam"
      ],
      "lunch": [
        "Masala Curry",
        "Rice",
        "Dal",
        "Sambar",
        "Veg Salad",
        "Pickle",
        "Chapathi"
      ],
      "snacks": ["Pokkuvada", "Tea", "Coffee"],
      "dinner": ["Chola", "Bhatoora", "Fried Rice", "Pickle", "Kheer"]
    },
    "sat": {
      "breakfast": [
        "Aloo Paratha",
        "Curd",
        "Tomato Chutney",
        "Tea",
        "Coffee",
        "Milk",
        "Bread",
        "Butter",
        "Jam"
      ],
      "lunch": [
        "Soyaben Curry",
        "Rice",
        "Dal",
        "Sambar",
        "Veg Salad",
        "Pickle",
        "Chapathi"
      ],
      "snacks": ["Sandwich", "Tea", "Coffee"],
      "dinner": [
        "Kofta",
        "Lokhi Dal Sabji",
        "Tomato Rice",
        "Chapathi",
        "Pickle"
      ]
    },
    "sun": {
      "breakfast": [
        "Pav",
        "Bhaji",
        "Poha",
        "Tea",
        "Coffee",
        "Milk",
        "Bread",
        "Butter",
        "Jam"
      ],
      "lunch": [
        "Shahi Paneer",
        "Rice",
        "Dal",
        "Sambar",
        "Veg Salad",
        "Pickle",
        "Chapathi"
      ],
      "snacks": ["Bread", "Pokkuvada", "Tea", "Coffee"],
      "dinner": ["Rajma", "Rice", "Dal", "Chapathi", "Sweet"]
    }
  },
  {
    "name": "New Mega Right Mess",
    "vegOnly": false,
    "mon": {
      "breakfast": [
        "Idly",
        "Vada",
        "Sambar",
        "Chutney",
        "Tea",
        "Coffee",
        "Milk",
        "Bread",
        "Butter",
        "Jam"
      ],
      "lunch": [
        "Fish Fry/Chicken Fry/Omlet",
        "Sabji",
        "Rasam",
        "Boiled Rice/Raw Rice",
        "Dal",
        "Sambar",
        "Thoran",
        "Curd/Sweets/Fruits",
        "Pickle",
        "Chapathi"
      ],
      "snacks": ["Veg Puff/Cake/Veg Bread Pakkoda", "Tea", "Coffee"],
      "dinner": ["Fried Chicken Curry", "Aloo Mutter Curry", "Ghee Rice", "Kerela Parotta", "Sweets"]
    },
    "tue": {
      "breakfast": [
        "Masala Dosa",
        "Chutney",
        "Sambar",
        "Tea",
        "Coffee",
        "Milk",
        "Bread",
        "Butter",
        "Jam"
      ],
      "lunch": [
        "Fish Fry/Chicken Curry/Omlet",
        "Sabji",
        "Rasam",
        "Boiled Rice/Raw Rice",
        "Dal",
        "Sambar",
        "Brissery",
        "Butter Milk",
        "Kadi Pakkoda",
        "Curd/Sweets/Fruits",
        "Pickle",
        "Chapathi"
      ],
      "snacks": ["Uzhunnu Vada/Cake", "Tea", "Coffee"],
      "dinner": [
        "Aloo Gobi",
        "Egg Curry/Omlet",
        "Dal",
        "Boiled Rice/Raw Rice",
        "Chapathi",
        "Sambar",
        "Pickle"
      ]
    },
    "wed": {
      "breakfast": [
        "Poori",
        "Aloo Curry",
        "Tea",
        "Coffee",
        "Milk",
        "Bread",
        "Butter",
        "Jam"
      ],
      "lunch": [
        "Aloo Brinjal",
        "Pappad",
        "Boiled Rice/Raw Rice",
        "Dal",
        "Pachakari",
        "Olan",
        "Rasam",
        "Veg Salad",
        "Pickle",
        "Chapathi",
        "Fish Fry/Chicken Curry/Omlet"
      ],
      "snacks": ["Cutlet", "Cupcake" , "Tea", "Coffee"],
      "dinner": [
        "Kadhai Chicken",
        "Fried Rice",
        "Gobi Manchurian",
        "Chapathi",
        "Sweets"
      ]
    },
    "thu": {
      "breakfast": [
        "Utthappam",
        "Chutney",
        "Sambar",
        "Noodles",
        "Tomato Sauce",
        "Tea",
        "Coffee",
        "Milk",
        "Bread",
        "Butter",
        "Jam"
      ],
      "lunch": [
        "Moru Curry",
        "Fish Curry",
        "Boiled Rice/Raw Rice",
        "Upperi",
        "Rasam",
        "Veg Salad",
        "Pickle",
        "Chapathi",
        "Curd/Sweets/Fruits"
      ],
      "snacks": ["Banana Bhajji/Cake/Pappadi", "Tea", "Coffee"],
      "dinner": ["White Chola Curry", "Bhatoora", "Ghee Rice", "Payasam/Ice Cream", "Pickle"]
    },
    "fri": {
      "breakfast": [
        "Puttu",
        "Poha",
        "Kadala Curry",
        "Tea",
        "Coffee",
        "Milk",
        "Bread",
        "Butter",
        "Jam"
      ],
      "lunch": [
        "Butter Paneer Masala",
        "Chicken Manthi",
        "Veg Manthi",
        "Mayonnaise",
        "Ice Cream"
      ],
      "snacks": ["Samosa/Cake", "Tea", "Coffee"],
      "dinner": ["Sabji", "Sambar", "Rasam", "Dal", "Boiled Rice/Raw Rice", "Chapathi", "Upperi"]
    },
    "sat": {
      "breakfast": [
        "Aloo Paratha",
        "Appam with Veg Curry",
        "Tomato Sauce",
        "Tea",
        "Coffee",
        "Milk",
        "Bread",
        "Butter",
        "Jam"
      ],
      "lunch": [
        "Soyaben Curry",
        "Boiled Rice/Raw Rice",
        "Dal",
        "Sambar",
        "Rasam",
        "Aloo Cabbage",
        "Fish Curry",
        "Chapathi", 
        "Payasam"
      ],
      "snacks": ["Sandwich", "Tea", "Coffee"],
      "dinner": [
        "Varutharcha Chicken Curry",
        "Paneer Potato Curry",
        "Biriyani Rice",
        "Chapathi",
        "Sweets"
      ]
    },
    "sun": {
      "breakfast": [
        "Poori",
        "Sabji",
        "Macaroni",
        "Tea",
        "Coffee",
        "Milk",
        "Bread",
        "Butter",
        "Jam"
      ],
      "lunch": [
        "Chicken Biriyani",
        "Veg Biriyani",
        "Veg Curry",
        "Curd",
        "Salad",
        "Pickle",
        "Sweets"
      ],
      "snacks": ["Cake", "Pakkoda", "Tea", "Coffee"],
      "dinner": ["Boiled Rice/Raw Rice", "Sambar", "Rasam", "Buttermilk", "Dal", "Bhindi Fry/Upperi", "Chapathi", "Pickle"]
    }
  },
  {
    "name": "C Mess",
    "vegOnly": true,
    "mon": {
      "breakfast": [
        "Poori Masala",
        "Tea",
        "Coffee",
        "Milk",
        "Bread",
        "Jam"
      ],
      "lunch": [
        "Aloo Matar",
        "Boiled Rice and White Rice",
        "Aviyal",
        "Sambar",
        "Rasam",
        "Pappadam",
        "Butter Milk",
        "Kondattam",
        "Pickle",
        "Fulka/Chapathi"
      ],
      "snacks": ["Ullivada", "Tea", "Coffee", "Milk"],
      "dinner": ["Green Peas Curry", "Lemon Rice", "Pickle", "Chapathi", "Salad", "Pappadam"]
    },
    "tue": {
      "breakfast": [
        "Puttu",
        "Pazham",
        "Kadala Curry",
        "Tea",
        "Coffee",
        "Milk",
        "Bread",
        "Jam"
      ],
      "lunch": [
        "Erissery",
        "Boiled Rice and White Rice",
        "Rasam",
        "Upperi",
        "Sabji",
        "Butter Milk",
        "Pappadam",
        "Kondattam",
        "Pickle",
        "Fulka/Chapathi",
        "Dal"
      ],
      "snacks": ["Uzhunnu Vada", "Chutney", "Tea", "Coffee"],
      "dinner": [
        "Chana Masala",
        "Bhatoora",
        "Ghee Rice",
        "Pickle"
      ]
    },
    "wed": {
      "breakfast": [
        "Aloo Paratha",
        "Sauce",
        "Tea",
        "Coffee",
        "Milk",
        "Bread",
        "Jam"
      ],
      "lunch": [
        "Boiled Rice and White Rice",
        "Rasam",
        "Upperi",
        "Pappadam",
        "Sabji",
        "Payasam",
        "Pickle",
        "Butter Milk",
        "Fulka/Chapathi",
        "Dal"
      ],
      "snacks": ["Sweets", "Tea", "Coffee", "Milk"],
      "dinner": [
        "Ghee Rice",
        "Chapathi",
        "Pappadam",
        "Salad",
        "Green Peas Curry",
        "Pickle"
      ]
    },
    "thu": {
      "breakfast": [
        "Masala Dosa",
        "Chutney",
        "Sambar",
        "Tea",
        "Coffee",
        "Milk",
        "Bread",
        "Jam"
      ],
      "lunch": [
        "Vegetable Biriyani",
        "Boiled Rice",
        "Rasam",
        "Salad",
        "Ice Cream",
        "Masala Curry",
        "Pickle",
        "Pappadam"
      ],
      "snacks": ["Cutlet", "Sauce", "Tea", "Coffee", "Milk"],
      "dinner": ["Boiled Rice and White Rice", "Sambar", "Rasam", "Pappadam", "Upperi", "Chapathi", "Pickle", "Sabji"]
    },
    "fri": {
      "breakfast": [
        "Vellappam",
        "Upma",
        "Cheru Payar Curry",
        "Ishtu",
        "Curry",
        "Tea",
        "Coffee",
        "Milk",
        "Bread",
        "Jam"
      ],
      "lunch": [
        "Boiled Rice and White Rice",
        "Mathan + Vanpayar Curry/Cheera Curry",
        "Koottucurry",
        "Rasam",
        "Upperi",
        "Pappadam",
        "Butter Milk",
        "Fulka/Chapathi",
        "Sabji",
        "Pickle"
      ],
      "snacks": ["North Samosa", "Cake", "Tea", "Coffee", "Milk"],
      "dinner": ["Aata Parotta", "Ghee Rice", "Green Peas Curry"]
    },
    "sat": {
      "breakfast": [
        "Dosa",
        "Sambar",
        "Chutney",
        "Tea",
        "Coffee",
        "Milk",
        "Bread",
        "Jam"
      ],
      "lunch": [
        "Boiled Rice and White Rice",
        "Puli Curry",
        "Rasam",
        "Upperi",
        "Pappadam",
        "Butter Milk",
        "Fulka/Chapathi",
        "Sabji",
        "Pickle"
      ],
      "snacks": ["Pakkoda", "Tea", "Coffee", "Milk"],
      "dinner": [
        "Jeeraka",
        "Masala Curry",
        "Tomato Rice",
        "Chapathi",
        "Salad"
      ]
    },
    "sun": {
      "breakfast": [
        "Poha",
        "Upma",
        "Tea",
        "Coffee",
        "Milk",
        "Bread",
        "Jam"
      ],
      "lunch": [
        "Boiled Rice and White Rice",
        "Sambar",
        "Upperi",
        "Pachady",
        "Rasam",
        "Butter Milk",
        "Fulka/Chapathi",
        "Sabji",
        "Pappadam",
        "Pickle"
      ],
      "snacks": ["Aloo Bonda", "Tea", "Coffee", "Milk"],
      "dinner": ["Uttappam", "Chutney", "Sambar", "Rice", "Pickle"]
    }
  }
]
